naicskit/__init__.py
naicskit/coder/__init__.py
naicskit/taxonomies/__init__.py
naicskit/taxonomies/isic_1968.json
naicskit/taxonomies/isic_1989.json
naicskit/taxonomies/isic_2002.json
naicskit/taxonomies/isic_2006.json
naicskit/taxonomies/isic_2024.json
naicskit/taxonomies/naics_2007.json
naicskit/taxonomies/naics_2012.json
naicskit/taxonomies/naics_2017.json
naicskit/taxonomies/naics_2022.json
naicskit/taxonomies/sic_1987.json
naicskit-0.1.0.dist-info/METADATA
naicskit-0.1.0.dist-info/WHEEL
naicskit-0.1.0.dist-info/RECORD
