Metadata-Version: 2.1
Name: naicskit
Version: 0.1.0
Summary: 
Author: deino475
Author-email: niledixon475@gmail.com
Requires-Python: >=3.6,<4.0
Classifier: Programming Language :: Python :: 3
Classifier: Programming Language :: Python :: 3.6
Classifier: Programming Language :: Python :: 3.7
Classifier: Programming Language :: Python :: 3.8
Classifier: Programming Language :: Python :: 3.9
Classifier: Programming Language :: Python :: 3.10
Classifier: Programming Language :: Python :: 3.11
Requires-Dist: torch (>=2.2.2,<3.0.0)
Requires-Dist: transformers (>=4.39.3,<5.0.0)
